quotonic/__init__.py
quotonic/aa.py
quotonic/clements.py
quotonic/fock.py
quotonic/logic.py
quotonic/nl.py
quotonic/perm.py
quotonic/qpnn.py
quotonic/trainer.py
quotonic/training_sets.py
quotonic/types.py
quotonic/utils.py
quotonic-1.0.1.dist-info/licenses/LICENSE
quotonic-1.0.1.dist-info/METADATA
quotonic-1.0.1.dist-info/WHEEL
quotonic-1.0.1.dist-info/top_level.txt
quotonic-1.0.1.dist-info/RECORD
