Metadata-Version: 2.4
Name: quotonic
Version: 1.0.1
Summary: A platform for performing efficient simulations of nonlinear quantum photonic circuits.
Author-email: Jacob Ewaniuk <jacob.ewaniuk@queensu.ca>
Maintainer-email: Jacob Ewaniuk <jacob.ewaniuk@queensu.ca>
License: MIT License
Project-URL: repository, https://github.com/jewaniuk/quotonic
Project-URL: documentation, https://jewaniuk.github.io/quotonic/
Keywords: quantum,photonics,optics,neural networks,machine learning,light-matter interactions
Classifier: Development Status :: 3 - Alpha
Classifier: Intended Audience :: Science/Research
Classifier: License :: OSI Approved :: MIT License
Classifier: Natural Language :: English
Classifier: Programming Language :: Python
Classifier: Programming Language :: Python :: 3
Classifier: Programming Language :: Python :: 3.10
Classifier: Programming Language :: Python :: 3.11
Classifier: Programming Language :: Python :: 3.12
Classifier: Topic :: Scientific/Engineering :: Artificial Intelligence
Classifier: Topic :: Scientific/Engineering :: Physics
Requires-Python: <4.0,>=3.10
License-File: LICENSE
Requires-Dist: numpy>=2.0.0
Requires-Dist: jax>=0.6.0
Requires-Dist: optax>=0.2.0
Provides-Extra: dev
Requires-Dist: build>=0.10.0; extra == "dev"
Requires-Dist: mypy>=0.981; extra == "dev"
Requires-Dist: pre-commit>=2.20.0; extra == "dev"
Requires-Dist: pytest>=7.2.0; extra == "dev"
Requires-Dist: pytest-cov>=4.0.0; extra == "dev"
Requires-Dist: flake8>=6.0.0; extra == "dev"
Requires-Dist: tox>=3.25.1; extra == "dev"
Requires-Dist: mkdocs>=1.4.2; extra == "dev"
Requires-Dist: mkdocs-material>=8.5.10; extra == "dev"
Requires-Dist: mkdocstrings>=0.19.0; extra == "dev"
Requires-Dist: mkdocstrings-python>=0.8.3; extra == "dev"
Requires-Dist: mike>=2.1.3; extra == "dev"
Requires-Dist: genbadge[coverage,flake8]>=1.1.0; extra == "dev"
Dynamic: license-file
